rofunc/__init__.py
rofunc/config/__init__.py
rofunc/config/utils.py
rofunc/config/__pycache__/__init__.cpython-38.pyc
rofunc/config/__pycache__/utils.cpython-38.pyc
rofunc/config/ikea/box_ivar_1.yaml
rofunc/config/ikea/shelf_liden_1.yaml
rofunc/config/learning/model_zoo.json
rofunc/config/learning/rl/config.yaml
rofunc/config/learning/rl/task/Ant.yaml
rofunc/config/learning/rl/task/CURICabinet.yaml
rofunc/config/learning/rl/task/CURICabinetBimanual.yaml
rofunc/config/learning/rl/task/CURICabinetImage.yaml
rofunc/config/learning/rl/task/Cartpole.yaml
rofunc/config/learning/rl/task/FrankaCabinet.yaml
rofunc/config/learning/rl/task/GymBaseTask.yaml
rofunc/config/learning/rl/task/HalfCheetah.yaml
rofunc/config/learning/rl/task/Hopper.yaml
rofunc/config/learning/rl/task/Humanoid.yaml
rofunc/config/learning/rl/task/HumanoidAMP.yaml
rofunc/config/learning/rl/task/HumanoidAMPHands.yaml
rofunc/config/learning/rl/task/HumanoidASEGetupSwordShield.yaml
rofunc/config/learning/rl/task/HumanoidASEHeadingSwordShield.yaml
rofunc/config/learning/rl/task/HumanoidASELocationSwordShield.yaml
rofunc/config/learning/rl/task/HumanoidASEPerturbSwordShield.yaml
rofunc/config/learning/rl/task/HumanoidASEReachSwordShield.yaml
rofunc/config/learning/rl/task/HumanoidASEStrikeSwordShield.yaml
rofunc/config/learning/rl/task/HumanoidViewMotion.yaml
rofunc/config/learning/rl/task/Reacher2d.yaml
rofunc/config/learning/rl/task/Walker2d.yaml
rofunc/config/learning/rl/task/humanoid_ase.yaml
rofunc/config/learning/rl/task/humanoid_ase_getup.yaml
rofunc/config/learning/rl/task/humanoid_ase_sword_shield.yaml
rofunc/config/learning/rl/task/humanoid_ase_sword_shield_getup.yaml
rofunc/config/learning/rl/task/humanoid_ase_sword_shield_getup_test.yaml
rofunc/config/learning/rl/task/humanoid_ase_sword_shield_test.yaml
rofunc/config/learning/rl/task/humanoid_sword_shield.yaml
rofunc/config/learning/rl/task/humanoid_sword_shield_heading.yaml
rofunc/config/learning/rl/task/humanoid_sword_shield_location.yaml
rofunc-0.0.2.5.dist-info/LICENSE
rofunc-0.0.2.5.dist-info/METADATA
rofunc-0.0.2.5.dist-info/WHEEL
rofunc-0.0.2.5.dist-info/entry_points.txt
rofunc-0.0.2.5.dist-info/top_level.txt
rofunc-0.0.2.5.dist-info/RECORD
