Metadata-Version: 2.1
Name: rofunc
Version: 0.0.2.5
Summary: Rofunc: The Full Process Python Package for Robot Learning from Demonstration and Robot Manipulation
Home-page: https://github.com/Skylark0924/Rofunc
Author: Junjia Liu
Author-email: jjliu@mae.cuhk.edu.hk
License: MIT
Keywords: robotics,learning from demonstration,reinforcement learning,robot manipulation
Classifier: Programming Language :: Python :: 3
Classifier: License :: OSI Approved :: MIT License
Classifier: Operating System :: OS Independent
Requires-Python: >=3.7,<3.9
License-File: LICENSE
Requires-Dist: cython (==3.0.0a10)
Requires-Dist: setuptools (==63.2.0)
Requires-Dist: pandas
Requires-Dist: tqdm (==4.65.0)
Requires-Dist: pillow (==9.5.0)
Requires-Dist: nestle (==0.2.0)
Requires-Dist: omegaconf (==2.3.0)
Requires-Dist: hydra-core (==1.3.2)
Requires-Dist: opencv-python (==4.7.0.72)
Requires-Dist: neurokit2 (==0.2.4)
Requires-Dist: gdown (==4.7.1)
Requires-Dist: pytz (==2023.3)
Requires-Dist: shutup (==0.2.0)
Requires-Dist: numpy (<=1.23.0)
Requires-Dist: matplotlib
Requires-Dist: open3d (==0.17.0)
Requires-Dist: transformers (==4.30.1)
Requires-Dist: gym (>=0.26.2)
Requires-Dist: gymnasium (>=0.28.1)
Requires-Dist: tensorboard
Requires-Dist: networkx
Requires-Dist: dgl
Provides-Extra: baselines
Requires-Dist: skrl (==0.10.2) ; extra == 'baselines'
Requires-Dist: ray[rllib] (==2.2.0) ; extra == 'baselines'
Requires-Dist: stable-baselines3 (==1.8.0) ; extra == 'baselines'
Requires-Dist: rl-games (==1.6.0) ; extra == 'baselines'
Requires-Dist: mujoco-py (==2.1.2.14) ; extra == 'baselines'
Requires-Dist: gym[all] (==0.26.2) ; extra == 'baselines'
Requires-Dist: gymnasium[all] (==0.28.1) ; extra == 'baselines'
Requires-Dist: mujoco-py (<2.2,>=2.1) ; extra == 'baselines'
